tgedr/pipeline/sink/__init__.py
tgedr/pipeline/sink/azure_storage_queue.py
tgedr_pipeline_sink-0.0.2.dist-info/LICENSE
tgedr_pipeline_sink-0.0.2.dist-info/METADATA
tgedr_pipeline_sink-0.0.2.dist-info/WHEEL
tgedr_pipeline_sink-0.0.2.dist-info/top_level.txt
tgedr_pipeline_sink-0.0.2.dist-info/RECORD
