Metadata-Version: 2.1
Name: tgedr-pipeline-sink
Version: 0.0.2
Summary: this package provides pipeline sink implementations
Home-page: https://github.com/tgedr/pipeline-sink
Author: joao tiago viegas
Author-email: jtviegas.js@gmail.com
License: Unlicense
Platform: UNKNOWN
Classifier: Programming Language :: Python :: 3
Classifier: Programming Language :: Python :: 3.7
License-File: LICENSE
Requires-Dist: pytest
Requires-Dist: configlookup
Requires-Dist: tgedr-pipeline-common (==0.1.10)
Requires-Dist: azure-storage-queue
